neofuzz/__init__.py
neofuzz/process.py
neofuzz/tokenization.py
neofuzz-0.4.0.dist-info/LICENSE
neofuzz-0.4.0.dist-info/METADATA
neofuzz-0.4.0.dist-info/WHEEL
neofuzz-0.4.0.dist-info/RECORD
