Metadata-Version: 2.3
Name: neofuzz
Version: 0.4.0
Summary: Blazing fast fuzzy text search for Python.
License: MIT
Author: Márton Kardos
Author-email: power.up1163@gmail.com
Requires-Python: >=3.8
Classifier: License :: OSI Approved :: MIT License
Classifier: Programming Language :: Python :: 3
Classifier: Programming Language :: Python :: 3.8
Classifier: Programming Language :: Python :: 3.9
Classifier: Programming Language :: Python :: 3.10
Classifier: Programming Language :: Python :: 3.11
Classifier: Programming Language :: Python :: 3.12
Classifier: Programming Language :: Python :: 3.13
Requires-Dist: annoy (>=1.17.3,<1.18.0)
Requires-Dist: joblib (>=1.4.0)
Requires-Dist: numpy (>=0.22.0)
Requires-Dist: scikit-learn (>=1.1.0)
Requires-Dist: thefuzz (>=0.22.0)
Requires-Dist: tokenizers (>=0.19.0)
